{
  "prompt_id": "add_02",
  "model": "llama3.2:3b",
  "category": "addition",
  "secret": "whisper",
  "raw_output": "The velvet sky, a canvas wide,\nA million stars, like diamonds side by side.\nThe world is hushed, a quiet sleep,\nAs darkness falls, and night's soft keep.\n\nThe moon, a glowing crescent shape,\nCasts shadows deep, in silence and escape.\nThe wind whispers secrets, through the trees so tall,\nAs night's mysterious veil, begins to fall.",
  "timestamp": "2026-06-22T17:17:00.593891Z"
}